igdbpy/__init__.py
igdbpy/utils.py
igdbpy/wrapper.py
igdbpy-0.1.1.dist-info/METADATA
igdbpy-0.1.1.dist-info/WHEEL
igdbpy-0.1.1.dist-info/licenses/LICENSE
igdbpy-0.1.1.dist-info/RECORD
