Metadata-Version: 2.4
Name: igdbpy
Version: 0.1.1
Summary: Python wrapper around the IGDB API
Author-email: TonyGrif <TonyGriffin2000@gmail.com>
License-Expression: MIT
License-File: LICENSE
Requires-Python: >=3.9
Requires-Dist: requests>=2.32.3
